[
  {
    "inputs": [],
    "name": "CoolDownBaby",
    "type": "error"
  },
  {
    "anonymous": false,
    "inputs": [
      {
        "indexed": false,
        "internalType": "address",
        "name": "previousAdmin",
        "type": "address"
      },
      {
        "indexed": false,
        "internalType": "address",
        "name": "newAdmin",
        "type": "address"
      }
    ],
    "name": "AdminChanged",
    "type": "event"
  },
  {
    "anonymous": false,
    "inputs": [
      {
        "indexed": true,
        "internalType": "address",
        "name": "beacon",
        "type": "address"
      }
    ],
    "name": "BeaconUpgraded",
    "type": "event"
  },
  {
    "anonymous": false,
    "inputs": [
      {
        "indexed": false,
        "internalType": "uint8",
        "name": "version",
        "type": "uint8"
      }
    ],
    "name": "Initialized",
    "type": "event"
  },
  {
    "anonymous": false,
    "inputs": [
      {
        "indexed": true,
        "internalType": "bytes32",
        "name": "role",
        "type": "bytes32"
      },
      {
        "indexed": true,
        "internalType": "bytes32",
        "name": "previousAdminRole",
        "type": "bytes32"
      },
      {
        "indexed": true,
        "internalType": "bytes32",
        "name": "newAdminRole",
        "type": "bytes32"
      }
    ],
    "name": "RoleAdminChanged",
    "type": "event"
  },
  {
    "anonymous": false,
    "inputs": [
      {
        "indexed": true,
        "internalType": "bytes32",
        "name": "role",
        "type": "bytes32"
      },
      {
        "indexed": true,
        "internalType": "address",
        "name": "account",
        "type": "address"
      },
      {
        "indexed": true,
        "internalType": "address",
        "name": "sender",
        "type": "address"
      }
    ],
    "name": "RoleGranted",
    "type": "event"
  },
  {
    "anonymous": false,
    "inputs": [
      {
        "indexed": true,
        "internalType": "bytes32",
        "name": "role",
        "type": "bytes32"
      },
      {
        "indexed": true,
        "internalType": "address",
        "name": "account",
        "type": "address"
      },
      {
        "indexed": true,
        "internalType": "address",
        "name": "sender",
        "type": "address"
      }
    ],
    "name": "RoleRevoked",
    "type": "event"
  },
  {
    "anonymous": false,
    "inputs": [
      {
        "indexed": true,
        "internalType": "address",
        "name": "implementation",
        "type": "address"
      }
    ],
    "name": "Upgraded",
    "type": "event"
  },
  {
    "inputs": [],
    "name": "DEFAULT_ADMIN_ROLE",
    "outputs": [
      {
        "internalType": "bytes32",
        "name": "",
        "type": "bytes32"
      }
    ],
    "stateMutability": "view",
    "type": "function"
  },
  {
    "inputs": [],
    "name": "SELLER_ROLE",
    "outputs": [
      {
        "internalType": "bytes32",
        "name": "",
        "type": "bytes32"
      }
    ],
    "stateMutability": "view",
    "type": "function"
  },
  {
    "inputs": [
      {
        "internalType": "uint128",
        "name": "amount",
        "type": "uint128"
      },
      {
        "internalType": "address",
        "name": "refUser",
        "type": "address"
      }
    ],
    "name": "buyNFT",
    "outputs": [],
    "stateMutability": "payable",
    "type": "function"
  },
  {
    "inputs": [
      {
        "internalType": "uint128",
        "name": "amount",
        "type": "uint128"
      },
      {
        "internalType": "uint256",
        "name": "saleId",
        "type": "uint256"
      },
      {
        "internalType": "address",
        "name": "refUser",
        "type": "address"
      }
    ],
    "name": "buyNFTOnSale",
    "outputs": [],
    "stateMutability": "payable",
    "type": "function"
  },
  {
    "inputs": [],
    "name": "getCurrentSale",
    "outputs": [
      {
        "components": [
          {
            "internalType": "uint64",
            "name": "start",
            "type": "uint64"
          },
          {
            "internalType": "uint64",
            "name": "duration",
            "type": "uint64"
          },
          {
            "internalType": "address",
            "name": "wlAddress",
            "type": "address"
          },
          {
            "internalType": "bool",
            "name": "isUSD",
            "type": "bool"
          },
          {
            "internalType": "uint128",
            "name": "amount",
            "type": "uint128"
          },
          {
            "internalType": "uint128",
            "name": "remainAmount",
            "type": "uint128"
          },
          {
            "internalType": "uint256",
            "name": "price",
            "type": "uint256"
          }
        ],
        "internalType": "struct Seller.Sale",
        "name": "",
        "type": "tuple"
      }
    ],
    "stateMutability": "view",
    "type": "function"
  },
  {
    "inputs": [],
    "name": "getReferralsContract",
    "outputs": [
      {
        "internalType": "address",
        "name": "",
        "type": "address"
      }
    ],
    "stateMutability": "view",
    "type": "function"
  },
  {
    "inputs": [
      {
        "internalType": "bytes32",
        "name": "role",
        "type": "bytes32"
      }
    ],
    "name": "getRoleAdmin",
    "outputs": [
      {
        "internalType": "bytes32",
        "name": "",
        "type": "bytes32"
      }
    ],
    "stateMutability": "view",
    "type": "function"
  },
  {
    "inputs": [
      {
        "internalType": "bytes32",
        "name": "role",
        "type": "bytes32"
      },
      {
        "internalType": "uint256",
        "name": "index",
        "type": "uint256"
      }
    ],
    "name": "getRoleMember",
    "outputs": [
      {
        "internalType": "address",
        "name": "",
        "type": "address"
      }
    ],
    "stateMutability": "view",
    "type": "function"
  },
  {
    "inputs": [
      {
        "internalType": "bytes32",
        "name": "role",
        "type": "bytes32"
      }
    ],
    "name": "getRoleMemberCount",
    "outputs": [
      {
        "internalType": "uint256",
        "name": "",
        "type": "uint256"
      }
    ],
    "stateMutability": "view",
    "type": "function"
  },
  {
    "inputs": [
      {
        "internalType": "uint256",
        "name": "saleId",
        "type": "uint256"
      }
    ],
    "name": "getSale",
    "outputs": [
      {
        "components": [
          {
            "internalType": "uint64",
            "name": "start",
            "type": "uint64"
          },
          {
            "internalType": "uint64",
            "name": "duration",
            "type": "uint64"
          },
          {
            "internalType": "address",
            "name": "wlAddress",
            "type": "address"
          },
          {
            "internalType": "bool",
            "name": "isUSD",
            "type": "bool"
          },
          {
            "internalType": "uint128",
            "name": "amount",
            "type": "uint128"
          },
          {
            "internalType": "uint128",
            "name": "remainAmount",
            "type": "uint128"
          },
          {
            "internalType": "uint256",
            "name": "price",
            "type": "uint256"
          }
        ],
        "internalType": "struct Seller.Sale",
        "name": "",
        "type": "tuple"
      }
    ],
    "stateMutability": "view",
    "type": "function"
  },
  {
    "inputs": [],
    "name": "getWallet",
    "outputs": [
      {
        "internalType": "address",
        "name": "",
        "type": "address"
      }
    ],
    "stateMutability": "view",
    "type": "function"
  },
  {
    "inputs": [
      {
        "internalType": "bytes32",
        "name": "role",
        "type": "bytes32"
      },
      {
        "internalType": "address",
        "name": "account",
        "type": "address"
      }
    ],
    "name": "grantRole",
    "outputs": [],
    "stateMutability": "nonpayable",
    "type": "function"
  },
  {
    "inputs": [
      {
        "internalType": "bytes32",
        "name": "role",
        "type": "bytes32"
      },
      {
        "internalType": "address",
        "name": "account",
        "type": "address"
      }
    ],
    "name": "hasRole",
    "outputs": [
      {
        "internalType": "bool",
        "name": "",
        "type": "bool"
      }
    ],
    "stateMutability": "view",
    "type": "function"
  },
  {
    "inputs": [
      {
        "internalType": "address",
        "name": "walletAddress",
        "type": "address"
      },
      {
        "internalType": "address",
        "name": "minterAddress",
        "type": "address"
      },
      {
        "internalType": "address",
        "name": "referralsAddress",
        "type": "address"
      }
    ],
    "name": "initialize",
    "outputs": [],
    "stateMutability": "nonpayable",
    "type": "function"
  },
  {
    "inputs": [],
    "name": "proxiableUUID",
    "outputs": [
      {
        "internalType": "bytes32",
        "name": "",
        "type": "bytes32"
      }
    ],
    "stateMutability": "view",
    "type": "function"
  },
  {
    "inputs": [
      {
        "internalType": "bytes32",
        "name": "role",
        "type": "bytes32"
      },
      {
        "internalType": "address",
        "name": "account",
        "type": "address"
      }
    ],
    "name": "renounceRole",
    "outputs": [],
    "stateMutability": "nonpayable",
    "type": "function"
  },
  {
    "inputs": [
      {
        "internalType": "bytes32",
        "name": "role",
        "type": "bytes32"
      },
      {
        "internalType": "address",
        "name": "account",
        "type": "address"
      }
    ],
    "name": "revokeRole",
    "outputs": [],
    "stateMutability": "nonpayable",
    "type": "function"
  },
  {
    "inputs": [
      {
        "internalType": "uint256",
        "name": "saleId",
        "type": "uint256"
      }
    ],
    "name": "setCurrentSaleId",
    "outputs": [],
    "stateMutability": "nonpayable",
    "type": "function"
  },
  {
    "inputs": [
      {
        "internalType": "address",
        "name": "referralsAddress",
        "type": "address"
      }
    ],
    "name": "setReferralsContract",
    "outputs": [],
    "stateMutability": "nonpayable",
    "type": "function"
  },
  {
    "inputs": [
      {
        "internalType": "uint256",
        "name": "saleId",
        "type": "uint256"
      },
      {
        "internalType": "uint64",
        "name": "start",
        "type": "uint64"
      },
      {
        "internalType": "uint64",
        "name": "duration",
        "type": "uint64"
      },
      {
        "internalType": "uint128",
        "name": "amount",
        "type": "uint128"
      },
      {
        "internalType": "address",
        "name": "wlAddress",
        "type": "address"
      },
      {
        "internalType": "bool",
        "name": "isUSD",
        "type": "bool"
      },
      {
        "internalType": "uint256",
        "name": "price",
        "type": "uint256"
      }
    ],
    "name": "setSale",
    "outputs": [],
    "stateMutability": "nonpayable",
    "type": "function"
  },
  {
    "inputs": [
      {
        "internalType": "address payable",
        "name": "walletAddress",
        "type": "address"
      }
    ],
    "name": "setWallet",
    "outputs": [],
    "stateMutability": "nonpayable",
    "type": "function"
  },
  {
    "inputs": [
      {
        "internalType": "bytes4",
        "name": "interfaceId",
        "type": "bytes4"
      }
    ],
    "name": "supportsInterface",
    "outputs": [
      {
        "internalType": "bool",
        "name": "",
        "type": "bool"
      }
    ],
    "stateMutability": "view",
    "type": "function"
  },
  {
    "inputs": [
      {
        "internalType": "address",
        "name": "newImplementation",
        "type": "address"
      }
    ],
    "name": "upgradeTo",
    "outputs": [],
    "stateMutability": "nonpayable",
    "type": "function"
  },
  {
    "inputs": [
      {
        "internalType": "address",
        "name": "newImplementation",
        "type": "address"
      },
      {
        "internalType": "bytes",
        "name": "data",
        "type": "bytes"
      }
    ],
    "name": "upgradeToAndCall",
    "outputs": [],
    "stateMutability": "payable",
    "type": "function"
  },
  {
    "stateMutability": "payable",
    "type": "receive"
  }
]
